Calculator/Calculator.py
Calculator/Test.py
Calculator/__init__.py
Calculator_Lin_Pel-0.1.3.dist-info/LICENSE.txt
Calculator_Lin_Pel-0.1.3.dist-info/METADATA
Calculator_Lin_Pel-0.1.3.dist-info/WHEEL
Calculator_Lin_Pel-0.1.3.dist-info/top_level.txt
Calculator_Lin_Pel-0.1.3.dist-info/RECORD
