Metadata-Version: 2.1
Name: Calculator-Lin-Pel
Version: 0.1.3
Summary: Basic Calculator
Author: Linas Peleckas
Author-email: <peleckas.l@gmail.com>
Keywords: python,calculations
Classifier: Development Status :: 1 - Planning
Classifier: Intended Audience :: Developers
Classifier: Programming Language :: Python :: 3
Classifier: Operating System :: Unix
Classifier: Operating System :: MacOS :: MacOS X
Classifier: Operating System :: Microsoft :: Windows
License-File: LICENSE.txt
